{"cameraMode":{"drawMode":0,"name":"Shaded","section":"Shading Mode"},"sceneLighting":true,"audioPlay":false,"sceneViewState":{"showFog":true,"showMaterialUpdate":false,"showSkybox":true,"showFlares":true,"showImageEffects":true,"showParticleSystems":true,"showVisualEffectGraphs":true,"m_FxEnabled":true},"in2DMode":false,"pivot":{"x":1.9443674087524415,"y":-8.89166259765625,"z":-4.5022053718566898},"rotation":{"x":0.48781654238700869,"y":0.47100162506103518,"z":-0.3579168915748596,"w":0.6419440507888794},"size":29.63038444519043,"orthographic":false}